CHANGES.txt
MANIFEST.in
README.rst
TODOS.rst
setup.py
src/collective/__init__.py
src/collective.googleauthenticator.egg-info/PKG-INFO
src/collective.googleauthenticator.egg-info/SOURCES.txt
src/collective.googleauthenticator.egg-info/dependency_links.txt
src/collective.googleauthenticator.egg-info/entry_points.txt
src/collective.googleauthenticator.egg-info/namespace_packages.txt
src/collective.googleauthenticator.egg-info/not-zip-safe
src/collective.googleauthenticator.egg-info/requires.txt
src/collective.googleauthenticator.egg-info/top_level.txt
src/collective/googleauthenticator/__init__.py
src/collective/googleauthenticator/adapter.py
src/collective/googleauthenticator/configure.zcml
src/collective/googleauthenticator/helpers.py
src/collective/googleauthenticator/interfaces.py
src/collective/googleauthenticator/overrides.zcml
src/collective/googleauthenticator/pas_plugin.py
src/collective/googleauthenticator/rebuild_i18n.sh
src/collective/googleauthenticator/setuphandlers.py
src/collective/googleauthenticator/testing.py
src/collective/googleauthenticator/userdataschema.py
src/collective/googleauthenticator/browser/__init__.py
src/collective/googleauthenticator/browser/configure.zcml
src/collective/googleauthenticator/browser/controlpanel.py
src/collective/googleauthenticator/browser/disable_two_factor_authentication.py
src/collective/googleauthenticator/browser/disable_two_factor_authentication_for_all_users.py
src/collective/googleauthenticator/browser/enable_two_factor_authentication_for_all_users.py
src/collective/googleauthenticator/browser/settings_helper.py
src/collective/googleauthenticator/browser/forms/__init__.py
src/collective/googleauthenticator/browser/forms/request_bar_code_reset.py
src/collective/googleauthenticator/browser/forms/reset_bar_code.py
src/collective/googleauthenticator/browser/forms/token.py
src/collective/googleauthenticator/browser/forms/user_setup.py
src/collective/googleauthenticator/browser/static/main.css
src/collective/googleauthenticator/browser/static/main.js
src/collective/googleauthenticator/browser/static/plone_ecmascript/popupforms.js
src/collective/googleauthenticator/locales/nl/LC_MESSAGES/collective.googleauthenticator.po
src/collective/googleauthenticator/profiles/default/actions.xml
src/collective/googleauthenticator/profiles/default/browserlayer.xml
src/collective/googleauthenticator/profiles/default/collective.googleauthenticator.marker.txt
