Metadata-Version: 1.1
Name: collective.googleauthenticator
Version: 0.2.5
Summary: Two-step verification for Plone 4 using the Google Authenticator app.
Home-page: https://github.com/collective/collective.googleauthenticator
Author: Goldmund, Wyldebeast & Wunderliebe
Author-email: info@gw20e.com
License: GPL 2.0
Keywords: google authenticator,two-step verification,multi-factor authentication,two-factor authentication
Platform: UNKNOWN
Classifier: Environment :: Web Environment
Classifier: Framework :: Plone
Classifier: Operating System :: OS Independent
Classifier: Programming Language :: Python
Classifier: Programming Language :: Python :: 2.6
Classifier: Programming Language :: Python :: 2.7
Classifier: Topic :: Software Development :: Libraries :: Python Modules
